danilacasito_drutils/__init__.py
danilacasito_drutils/network.py
danilacasito_drutils/parse.py
danilacasito_drutils-0.1.8.dist-info/LICENSE
danilacasito_drutils-0.1.8.dist-info/WHEEL
danilacasito_drutils-0.1.8.dist-info/METADATA
danilacasito_drutils-0.1.8.dist-info/RECORD
